odoo/addons/account_financial_report_block_pdf/README.rst
odoo/addons/account_financial_report_block_pdf/__init__.py
odoo/addons/account_financial_report_block_pdf/__manifest__.py
odoo/addons/account_financial_report_block_pdf/data/ir_config_param.xml
odoo/addons/account_financial_report_block_pdf/i18n/ca_ES.po
odoo/addons/account_financial_report_block_pdf/i18n/es.po
odoo/addons/account_financial_report_block_pdf/static/description/icon.png
odoo/addons/account_financial_report_block_pdf/wizard/__init__.py
odoo/addons/account_financial_report_block_pdf/wizard/abstract_wizard.py
odoo/addons/account_financial_report_block_pdf/wizard/aged_partner_balance_wizard.py
odoo/addons/account_financial_report_block_pdf/wizard/general_ledger_report_wizard.py
odoo/addons/account_financial_report_block_pdf/wizard/journal_ledger_wizard.py
odoo/addons/account_financial_report_block_pdf/wizard/open_items_wizard.py
odoo/addons/account_financial_report_block_pdf/wizard/trial_balance_wizard.py
odoo/addons/account_financial_report_block_pdf/wizard/vat_report_wizard.py
odoo12_addon_account_financial_report_block_pdf-12.0.1.0.0.dist-info/METADATA
odoo12_addon_account_financial_report_block_pdf-12.0.1.0.0.dist-info/WHEEL
odoo12_addon_account_financial_report_block_pdf-12.0.1.0.0.dist-info/top_level.txt
odoo12_addon_account_financial_report_block_pdf-12.0.1.0.0.dist-info/RECORD
